conn2svg/__init__.py
conn2svg/_tooling.py
conn2svg/conn2svg.py
conn2svg-0.0.7.dist-info/LICENSE
conn2svg-0.0.7.dist-info/METADATA
conn2svg-0.0.7.dist-info/WHEEL
conn2svg-0.0.7.dist-info/top_level.txt
conn2svg-0.0.7.dist-info/RECORD
